KaiyuanShijieLvxingShouce/README.md
KaiyuanShijieLvxingShouce/__init__.py
KaiyuanShijieLvxingShouce/__main__.py
KaiyuanShijieLvxingShouce/file.epub
KaiyuanShijieLvxingShouce/index.html
KaiyuanShijieLvxingShouce/css/__init__.py
KaiyuanShijieLvxingShouce/css/annotations.css
KaiyuanShijieLvxingShouce/css/main.css
KaiyuanShijieLvxingShouce/css/normalize.css
KaiyuanShijieLvxingShouce/css/popup.css
KaiyuanShijieLvxingShouce/font/__init__.py
KaiyuanShijieLvxingShouce/font/fontello.eot
KaiyuanShijieLvxingShouce/font/fontello.svg
KaiyuanShijieLvxingShouce/font/fontello.ttf
KaiyuanShijieLvxingShouce/font/fontello.woff
KaiyuanShijieLvxingShouce/img/__init__.py
KaiyuanShijieLvxingShouce/img/annotator-glyph-sprite.png
KaiyuanShijieLvxingShouce/img/annotator-icon-sprite.png
KaiyuanShijieLvxingShouce/img/apple-touch-icon.png
KaiyuanShijieLvxingShouce/img/cancelfullscreen.png
KaiyuanShijieLvxingShouce/img/close.png
KaiyuanShijieLvxingShouce/img/fullscreen.png
KaiyuanShijieLvxingShouce/img/loader.gif
KaiyuanShijieLvxingShouce/img/menu-icon.png
KaiyuanShijieLvxingShouce/img/save.png
KaiyuanShijieLvxingShouce/img/saved.png
KaiyuanShijieLvxingShouce/img/settings-s.png
KaiyuanShijieLvxingShouce/img/settings.png
KaiyuanShijieLvxingShouce/img/star.png
KaiyuanShijieLvxingShouce/js/__init__.py
KaiyuanShijieLvxingShouce/js/epub.js
KaiyuanShijieLvxingShouce/js/epub.min.js
KaiyuanShijieLvxingShouce/js/epub.min.map
KaiyuanShijieLvxingShouce/js/hooks.min.js
KaiyuanShijieLvxingShouce/js/hooks.min.map
KaiyuanShijieLvxingShouce/js/reader.js
KaiyuanShijieLvxingShouce/js/reader.js.map
KaiyuanShijieLvxingShouce/js/reader.min.js
KaiyuanShijieLvxingShouce/js/reader.min.map
KaiyuanShijieLvxingShouce/js/hooks/__init__.py
KaiyuanShijieLvxingShouce/js/hooks/extensions/__init__.py
KaiyuanShijieLvxingShouce/js/hooks/extensions/highlight.js
KaiyuanShijieLvxingShouce/js/libs/__init__.py
KaiyuanShijieLvxingShouce/js/libs/jquery.min.js
KaiyuanShijieLvxingShouce/js/libs/localforage.min.js
kaiyuan_shijie_lvxing_shouce-2024.3.1.0.dist-info/METADATA
kaiyuan_shijie_lvxing_shouce-2024.3.1.0.dist-info/WHEEL
kaiyuan_shijie_lvxing_shouce-2024.3.1.0.dist-info/entry_points.txt
kaiyuan_shijie_lvxing_shouce-2024.3.1.0.dist-info/top_level.txt
kaiyuan_shijie_lvxing_shouce-2024.3.1.0.dist-info/RECORD
